pa1010d/__init__.py
pa1010d-0.0.4.dist-info/LICENSE.txt
pa1010d-0.0.4.dist-info/METADATA
pa1010d-0.0.4.dist-info/WHEEL
pa1010d-0.0.4.dist-info/top_level.txt
pa1010d-0.0.4.dist-info/RECORD
